pymeow/__init__.py
pymeow/client.py
pymeow/exceptions.py
pymeow/models.py
pymeow/utils.py
PyMeow-1.0.1.dist-info/LICENSE
PyMeow-1.0.1.dist-info/METADATA
PyMeow-1.0.1.dist-info/WHEEL
PyMeow-1.0.1.dist-info/top_level.txt
PyMeow-1.0.1.dist-info/RECORD
