Metadata-Version: 2.1
Name: PyMeow
Version: 1.0.1
Summary: A simple python wrapper for using API of https://thecatapi.com/
Author-email: funnyruler <funnyruler7@gmail.com>
Project-URL: Homepage, https://github.com/funnyruler/pymeow
Project-URL: Issues, https://github.com/funnyruler/pymeow/issues
Project-URL: Examples, https://github.com/funnyruler/pymeow/tree/main/examples
Classifier: Programming Language :: Python :: 3
Classifier: License :: OSI Approved :: MIT License
Classifier: Operating System :: OS Independent
Requires-Python: >=3.7
License-File: LICENSE
